fragmentsoup.py
fragmentsoup-0.6.1.dist-info/METADATA
fragmentsoup-0.6.1.dist-info/WHEEL
fragmentsoup-0.6.1.dist-info/top_level.txt
fragmentsoup-0.6.1.dist-info/zip-safe
fragmentsoup-0.6.1.dist-info/RECORD
