Metadata-Version: 2.1
Name: fragmentsoup
Version: 0.6.1
Summary: A wrapper for BeautifulSoup4 that restores the ability to work with HTML fragments
Home-page: https://github.com/VanL/FragmentSoup
Author: VanL
Author-email: van.lindberg+fragmentsoup@gmail.com
Maintainer: VanL
Maintainer-email: van.lindberg+fragmentsoup@gmail.com
License: MIT license
Keywords: fragmentsoup,beautifulsoup,beautifulsoup4
Platform: UNKNOWN
Classifier: Development Status :: 3 - Alpha
Classifier: Intended Audience :: Developers
Classifier: Programming Language :: Python :: 3.6
Classifier: Programming Language :: Python :: 3.7
Classifier: Programming Language :: Python :: 3.8
Classifier: License :: OSI Approved :: MIT License
Classifier: Topic :: Software Development :: Libraries
Requires-Dist: beautifulsoup4
